odoo/addons/l10n_nl_base_ubl/README.rst
odoo/addons/l10n_nl_base_ubl/__init__.py
odoo/addons/l10n_nl_base_ubl/__manifest__.py
odoo/addons/l10n_nl_base_ubl/i18n/l10n_nl_base_ubl.pot
odoo/addons/l10n_nl_base_ubl/models/__init__.py
odoo/addons/l10n_nl_base_ubl/models/base_ubl.py
odoo/addons/l10n_nl_base_ubl/readme/CONTRIBUTORS.rst
odoo/addons/l10n_nl_base_ubl/readme/DESCRIPTION.rst
odoo/addons/l10n_nl_base_ubl/static/description/icon.png
odoo/addons/l10n_nl_base_ubl/static/description/index.html
odoo/addons/l10n_nl_base_ubl/tests/__init__.py
odoo/addons/l10n_nl_base_ubl/tests/test_ubl_at_install.py
odoo/addons/l10n_nl_base_ubl/tests/test_ubl_post_install.py
odoo13_addon_l10n_nl_base_ubl-13.0.1.0.1.dev7.dist-info/METADATA
odoo13_addon_l10n_nl_base_ubl-13.0.1.0.1.dev7.dist-info/WHEEL
odoo13_addon_l10n_nl_base_ubl-13.0.1.0.1.dev7.dist-info/top_level.txt
odoo13_addon_l10n_nl_base_ubl-13.0.1.0.1.dev7.dist-info/RECORD
